pykwg/__init__.py
pykwg/config.py
pykwg/ontology/KWGOntology.py
pykwg-0.0.1.dist-info/LICENSE
pykwg-0.0.1.dist-info/METADATA
pykwg-0.0.1.dist-info/WHEEL
pykwg-0.0.1.dist-info/RECORD
