Metadata-Version: 2.1
Name: pykwg
Version: 0.0.1
Summary: Package for interacting with KnowWhereGraph
Author: ThomasThelen
Author-email: tommythelen@gmail.com
Requires-Python: >=3.10,<4.0
Classifier: Programming Language :: Python :: 3
Classifier: Programming Language :: Python :: 3.10
Classifier: Programming Language :: Python :: 3.11
Requires-Dist: rdflib (>=7.0.0,<8.0.0)
